LICENSE
MANIFEST.in
README.md
setup.cfg
setup.py
tap_freshsales/__init__.py
tap_freshsales/tap_utils.py
tap_freshsales.egg-info/PKG-INFO
tap_freshsales.egg-info/SOURCES.txt
tap_freshsales.egg-info/dependency_links.txt
tap_freshsales.egg-info/entry_points.txt
tap_freshsales.egg-info/requires.txt
tap_freshsales.egg-info/top_level.txt
tap_freshsales/schemas/accounts.json
tap_freshsales/schemas/appointments.json
tap_freshsales/schemas/contacts.json
tap_freshsales/schemas/deals.json
tap_freshsales/schemas/leads.json
tap_freshsales/schemas/sales_activities.json
tap_freshsales/schemas/tasks.json