Metadata-Version: 1.1
Name: tap-freshsales
Version: 0.1.1
Summary: Singer.io tap for extracting FreshSales Data
Home-page: http://singer.io
Author: Tisham Dhar (Lori)
Author-email: UNKNOWN
License: UNKNOWN
Platform: UNKNOWN
Classifier: Programming Language :: Python :: 3 :: Only
